{"_ts":[1541050208],"_r":{"breakdown":{"html":{"bytes":[133723],"requests":[10]},"js":{"bytes":[1311081],"requests":[58]},"css":{"bytes":[159663],"requests":[9]},"image":{"bytes":[135288],"requests":[29]},"flash":{"bytes":[0],"requests":[0]},"font":{"bytes":[81294],"requests":[4]},"video":{"bytes":[0],"requests":[0]},"other":{"bytes":[16329],"requests":[20]}},"date":[1541050208],"domElements":[1236],"domInteractive":[4304],"firstPaint":[3924.2999999988],"fullyLoaded":[25567],"id":["181101_WJ_61b632f9c88460b0b693c3b2ccab50f8"],"loadTime":[25567],"render":[3996],"SpeedIndex":[5073],"TTFB":[1958],"videoFrames":[[{"_i":"ms_000000.jpg","_t":0,"_vc":0},{"_i":"ms_003996.jpg","_t":3996,"_vc":26},{"_i":"ms_004061.jpg","_t":4061,"_vc":30},{"_i":"ms_004108.jpg","_t":4108,"_vc":87},{"_i":"ms_004247.jpg","_t":4247,"_vc":87},{"_i":"ms_004287.jpg","_t":4287,"_vc":87},{"_i":"ms_004305.jpg","_t":4305,"_vc":88},{"_i":"ms_004345.jpg","_t":4345,"_vc":88},{"_i":"ms_004364.jpg","_t":4364,"_vc":88},{"_i":"ms_004402.jpg","_t":4402,"_vc":88},{"_i":"ms_004518.jpg","_t":4518,"_vc":88},{"_i":"ms_004632.jpg","_t":4632,"_vc":87},{"_i":"ms_005740.jpg","_t":5740,"_vc":88},{"_i":"ms_006073.jpg","_t":6073,"_vc":88},{"_i":"ms_006108.jpg","_t":6108,"_vc":88},{"_i":"ms_006204.jpg","_t":6204,"_vc":88},{"_i":"ms_006311.jpg","_t":6311,"_vc":88},{"_i":"ms_006727.jpg","_t":6727,"_vc":87},{"_i":"ms_009609.jpg","_t":9609,"_vc":87},{"_i":"ms_009906.jpg","_t":9906,"_vc":87},{"_i":"ms_010006.jpg","_t":10006,"_vc":87},{"_i":"ms_010103.jpg","_t":10103,"_vc":88},{"_i":"ms_010204.jpg","_t":10204,"_vc":98},{"_i":"ms_012123.jpg","_t":12123,"_vc":98},{"_i":"ms_015315.jpg","_t":15315,"_vc":98},{"_i":"ms_015851.jpg","_t":15851,"_vc":98},{"_i":"ms_016624.jpg","_t":16624,"_vc":99},{"_i":"ms_016852.jpg","_t":16852,"_vc":99},{"_i":"ms_016919.jpg","_t":16919,"_vc":99},{"_i":"ms_017021.jpg","_t":17021,"_vc":99},{"_i":"ms_017116.jpg","_t":17116,"_vc":99},{"_i":"ms_017209.jpg","_t":17209,"_vc":99},{"_i":"ms_017310.jpg","_t":17310,"_vc":99},{"_i":"ms_017624.jpg","_t":17624,"_vc":99},{"_i":"ms_017727.jpg","_t":17727,"_vc":99},{"_i":"ms_017812.jpg","_t":17812,"_vc":99},{"_i":"ms_017933.jpg","_t":17933,"_vc":99},{"_i":"ms_020225.jpg","_t":20225,"_vc":99},{"_i":"ms_020302.jpg","_t":20302,"_vc":99},{"_i":"ms_020405.jpg","_t":20405,"_vc":99},{"_i":"ms_020505.jpg","_t":20505,"_vc":99},{"_i":"ms_020623.jpg","_t":20623,"_vc":99},{"_i":"ms_025195.jpg","_t":25195,"_vc":99},{"_i":"ms_025214.jpg","_t":25214,"_vc":99},{"_i":"ms_025312.jpg","_t":25312,"_vc":99},{"_i":"ms_025414.jpg","_t":25414,"_vc":99},{"_i":"ms_025508.jpg","_t":25508,"_vc":99},{"_i":"ms_025567.jpg","_t":25567,"_vc":100}]],"visualComplete":[25567],"lighthouse":[31],"pagespeed":[85]}}