{"_ts":[1538420680,1538464011],"_r":{"breakdown":{"html":{"bytes":[113727,111606],"requests":[16,15]},"js":{"bytes":[2040243,1993687],"requests":[58,58]},"css":{"bytes":[139510,140709],"requests":[8,8]},"image":{"bytes":[244297,244294],"requests":[31,31]},"flash":{"bytes":[0,0],"requests":[0,0]},"font":{"bytes":[71557,71629],"requests":[3,3]},"video":{"bytes":[0,0],"requests":[0,0]},"other":{"bytes":[44920,44734],"requests":[24,23]}},"date":[1538420680,1538464011],"domElements":[636,636],"domInteractive":[1212,1061],"firstPaint":[997.9999999996,897.2999999969],"fullyLoaded":[6933,6546],"id":["181001_08_ae2b945563a63fa50e7f9b70e9d8794e","181002_86_494bd42497d8f7e79c981249f025393f"],"loadTime":[5820,5406],"render":[1000,900],"SpeedIndex":[1989,1824],"TTFB":[268,317],"videoFrames":[[{"_i":"ms_000000.jpg","_t":0,"_vc":0},{"_i":"ms_001000.jpg","_t":1000,"_vc":60},{"_i":"ms_001100.jpg","_t":1100,"_vc":60},{"_i":"ms_001200.jpg","_t":1200,"_vc":59},{"_i":"ms_001300.jpg","_t":1300,"_vc":79},{"_i":"ms_002400.jpg","_t":2400,"_vc":79},{"_i":"ms_002500.jpg","_t":2500,"_vc":79},{"_i":"ms_003900.jpg","_t":3900,"_vc":81},{"_i":"ms_004000.jpg","_t":4000,"_vc":80},{"_i":"ms_004100.jpg","_t":4100,"_vc":80},{"_i":"ms_004400.jpg","_t":4400,"_vc":82},{"_i":"ms_004700.jpg","_t":4700,"_vc":82},{"_i":"ms_004900.jpg","_t":4900,"_vc":81},{"_i":"ms_005200.jpg","_t":5200,"_vc":81},{"_i":"ms_005400.jpg","_t":5400,"_vc":81},{"_i":"ms_005500.jpg","_t":5500,"_vc":81},{"_i":"ms_005600.jpg","_t":5600,"_vc":100}],[{"_i":"ms_000000.jpg","_t":0,"_vc":0},{"_i":"ms_000900.jpg","_t":900,"_vc":59},{"_i":"ms_001000.jpg","_t":1000,"_vc":59},{"_i":"ms_001100.jpg","_t":1100,"_vc":80},{"_i":"ms_001300.jpg","_t":1300,"_vc":80},{"_i":"ms_001400.jpg","_t":1400,"_vc":80},{"_i":"ms_001500.jpg","_t":1500,"_vc":79},{"_i":"ms_002200.jpg","_t":2200,"_vc":78},{"_i":"ms_002300.jpg","_t":2300,"_vc":79},{"_i":"ms_004100.jpg","_t":4100,"_vc":81},{"_i":"ms_004400.jpg","_t":4400,"_vc":80},{"_i":"ms_004500.jpg","_t":4500,"_vc":81},{"_i":"ms_004800.jpg","_t":4800,"_vc":81},{"_i":"ms_005100.jpg","_t":5100,"_vc":81},{"_i":"ms_005200.jpg","_t":5200,"_vc":95},{"_i":"ms_005300.jpg","_t":5300,"_vc":100}]],"visualComplete":[5600,5300],"lighthouse":[31,31],"pagespeed":[80,80]}}